tm35fin/__init__.py
tm35fin/coordinates.py
tm35fin-0.1.1.dist-info/LICENSE
tm35fin-0.1.1.dist-info/METADATA
tm35fin-0.1.1.dist-info/WHEEL
tm35fin-0.1.1.dist-info/top_level.txt
tm35fin-0.1.1.dist-info/RECORD
