Metadata-Version: 2.1
Name: tm35fin
Version: 0.1.1
Summary: ETRS-TM35FIN coordinate system
Home-page: https://github.com/vaizki/python-tm35fin
Author: Jukka Vaisanen
Author-email: vaizki@vaizki.fi
License: UNKNOWN
Project-URL: Bug Tracker, https://github.com/vaizki/python-tm35fin/issues
Platform: UNKNOWN
Classifier: Programming Language :: Python :: 3
Classifier: License :: OSI Approved :: MIT License
Classifier: Operating System :: OS Independent
Requires-Python: >=3.8
License-File: LICENSE
